{
  "generator-jhipster": {
    "applicationType": "monolith",
    "gitHubOrganization": "luizlucasi",
    "baseName": "jhipsterSampleApplicationNova",
    "packageName": "io.github.jhipster.application",
    "packageFolder": "io/github/jhipster/application",
    "serverPort": 8080,
    "serviceDiscoveryType": false,
    "authenticationType": "oauth2",
    "uaaBaseName": "../uaa",
    "cacheProvider": "no",
    "enableHibernateCache": false,
    "websocket": false,
    "databaseType": "sql",
    "devDatabaseType": "h2Memory",
    "prodDatabaseType": "mysql",
    "searchEngine": false,
    "enableSwaggerCodegen": false,
    "messageBroker": false,
    "buildTool": "maven",
    "useSass": false,
    "clientPackageManager": "yarn",
    "testFrameworks": [],
    "enableTranslation": false,
    "nativeLanguage": "en",
    "languages": [
      "en"
    ],
    "clientFramework": "angularX",
    "jhiPrefix": "jhi"
  }
}